{"task_id": "3b9994b91a6da1b4", "source": "Approach to Internal Medicine_ A Resource Book for Clinical Practice ( PDFDrive ).pdf (Part 288/464)", "text": "d symptom free periods in\n278\nRheumatoid Arthritis\n\n--- Page 300 ---\nSPECIFIC ENTITIES (CONT\u2019D)\nbetween for days to months. May be anti CCP posi\ntive and occasionally progresses to other rheumatic\ndisorders (RA, SLE). Treatment with hydroxychloro\nquine can be useful\nSJOGREN\u2019S SYNDROME (KERATOCONJUNCTIVITIS\nSICCA)\n\u0002\nPATHOPHYSIOLOGY\nCD4 lymphocytic infiltration of\nsalivary and lacrimal glands\n\u0002\nCAUSES\nprimary (sicca plus episodic, non deform\ning polyarthritis), secondary (RA, SLE, scleroderma,\npolyarteritis nodosa, polymyositis, HIV)\n\u0002\nCLINICAL FEATURES\nsicca (dry eyes and dry mouth,\nalong with impaired taste, parotid gland enlarge\nment,\ndental\ncaries),\ndyspareunia,\narthralgia,\narthritis, and constitutional symptoms. May be\nassociated with Raynaud\u2019s phenomenon, cuta\nneous vasculitis, cerebritis, CNS vasculitis, stroke,\nand peripheral neuropathy\n\u0002\nINVESTIGATIONS\nquantitative Ig (polyclonal IgG),\nRF, ANA, ENA (SS A, SS B). Check for secondary\ncauses\n\u0002\nTREATMENTS\nsymptomatic (artificial tears, pilocar\npine 5 mg PO QID), hydroxychloroquine\nLOFGREN\u2019S\nSYNDROME\na\nbenign\nself limited\nform of sarcoidosis. Tetrad of erythema nodosum,\nhilar lymphadenopathy, arthritis (ankles and some\ntimes knees), and uveitis\nSPECIFIC ENTITIES (CONT\u2019D)\nRESPIRATORY DISEASES IN RHEUMATOID\nARTHRITIS\n\u0002\nAIRWAY\ncricoarytenoid\narthritis\nwith\ncentral\nairway obstruction, bronchiectasis, obliterative\nbronchiolitis, chronic small airway obstruction\n\u0002\nPARENCHYMA\npneumonia\n(particularly\nwith\nimmunosuppression), interstitial fibrosis, bronch\niolitis obliterans with organizing pneumonia, rheu\nmatoid nodules, rheumatoid pneumoconiosis,\napical fibrobullous disease, drug related pneumo\nnitis and fibrosis (methotrexate, gold, penicilla\nmine, NSAIDs, cyclophosphamide, azathioprine,\nsulfasalazine)\n\u0002\nVASCULAR\npulmonary hypertension, vasculitis\n\u0002\nPLEURAL\npleuritis,\npleural\neffusion,\npleural\nthickening\nUNDIFFERENTIATED CONNECTIVE TISSUE DIS\nEASE\noverlap syndrome with clinical features of\ntwo or more rheumatologic disorders (RA, SLE, Sjog\nren\u2019s syndrome, scleroderma, inflammatory myopa\nthies) but does not fit the diagnostic criteria for any\nspecific disorder\nMIXED CONNECTIVE TISSUE DISEASE\na specific\noverlap syndrome with clinical features of SLE, scler\noderma, polymyositis, and antibodies to RNP. Char\nacteristically, Raynaud\u2019s phenomenon, myositis, and\nsynovitis are present\nSystemic Lupus Erythematosus\nPATHOPHYSIOLOGY\nPOPULATION\ntypically affects women aged 15 45\nAUTOIMMUNE\nREACTION\nantibody immune\ncomplex deposition in kidneys (glomerulonephri\ntis), autoantibodies against cell surface antigens\non hematopoietic progenitor cells (anemia, neutro\npenia, thrombocytopenia), antiphospholipid anti\nbodies (thrombosis)\nACR DIAGNOSTIC CRITERIA w4 RASHESw\n\u0002 4 rashes\nmalar rash, discoid rash, oral ulcers,\nphotosensitivity\n\u0002 Renal\nproteinuria >0.5 g/day or \u00043+, or cellular\ncasts)\n\u0002 Arthritis \u00042 peripheral joints, non erosive\n\u0002 Serositis\npleuritis, pericarditis\n\u0002 Hematologic\nhemolytic anemia, leukopenia <4.0\n\u0005109/L, lymphopenia <1.5x109/L, thrombocytope\nnia <100x109/L\n\u0002 Excitation\nseizures, psychosis\n\u0002 Serology\nANA, anti dsDNA, anti Smith, antipho\nspholipid antibodies, false positive VDRL\nPATHOPHYSIOLOGY (CONT\u2019D)\nNeed \u00044 of 11 criteria (each rash counts as one\ncriterion and ANA as a separate criterium) to make\ndiagnosis. Note that many patients may not ever fulfill\nfour criteria until several years into their disease course\nCLINICAL FEATURES\nJOINT SYMPTOMS\nsymmetric non erosive polyar\nthritis with joint pain, swelling, redness, morning\nstiffness (>1 h), and dysfunction. Sens 88%\n\u0002\nHANDS\nJaccoud\u2019s arthritis (joint deformities are\nunusual). Fingers and wrists may be involved\n\u0002\nLEGS\nknees more commonly affected\n\u0002\nAVASCULAR NECROSIS\nhip, shoulder, and knee may\nbe affected\nEXTRA ARTICULAR MANIFESTATIONS\n\u0002\nPULMONARY\npleuritis\n(sens\n50%),\npulmonary\nhypertension, PE, shrinking lung syndrome (dys\npnea, pleuritic chest pain, progressive reduction in\nlung volume, elevated diaphragms)\n\u0002\nCARDIAC\npericarditis (sens 30%), myocarditis, Lib\nman Sacks endocarditis\nSystemic Lupus Erythematosus\n279", "text_length": 4087, "metadata": {"source": "Approach to Internal Medicine_ A Resource Book for Clinical Practice ( PDFDrive ).pdf (Part 288/464)", "type": "chunk", "chunk_index": 287, "total_chunks": 464, "uploaded_by": "admin@admin.com", "upload_date": "2025-12-11T18:40:09.641206", "document_uuid": "fda2cab4-cdd9-4015-af24-46fd62c86d94", "filename": "Approach to Internal Medicine_ A Resource Book for Clinical Practice ( PDFDrive ).pdf", "category": "medical_pdf", "section": "body", "year": null, "outdated": false, "document_id": "fda2cab4-cdd9-4015-af24-46fd62c86d94"}, "created_at": "2025-12-11T18:40:09.641894", "status": "complete", "chunks_added": 3}