{"task_id": "69e96649229bb41e", "source": "8205Oxford Handbook of Clinical Medicine 10th 2017 Edition_SamanSarKo - Copy.pdf (Part 821/905)", "text": " but still \nmonitor and repeat ABG.\nOxygen therapy\n\n--- Page 827 ---\nEmergencies\n813\n\ue098 Management of acute COPD\nControlled oxygen therapy if SaO2 <88% or PaO2 <7 kPa:\nStart at 24\u201328%, aim sats 88\u201392%\nAdjust according to ABG, aim PaO2 >8.0kPa with a rise in PaCO2 <1.5kPa\nNebulized bronchodilators:\nSalbutamol 5mg/4h and ipratropium 500mcg/6h\nInvestigate: CXR, ABG\nSteroids:\nIV hydrocortisone 200mg and oral prednisolone\n30mg OD (continue for 7\u201314d)\nAntibiotics:\nUse if evidence of infection, eg amoxicillin 500mg/8h PO,\nalternatively clarithromycin or doxycycline (p387)\nPhysiotherapy to aid sputum expectoration\nIf no response to nebulizers and steroids:\nConsider IV aminophylline*\nIf no response:\n1   Consider non-invasive positive pressure ventilation\u2020 (NIPPV) if \nrespiratory rate >30 or pH <7.35, or PaCO2 rising despite best \nmedical treatment. OR:\n2   Consider a respiratory stimulant drug, eg doxapram 1.5\u20134mg/\nmin IV in patients who are not suitable for mechanical ventila-\ntion. SE: agitation, confusion, tachycardia, nausea. It is a \nshort-term measure, used only if NIV is not available\nConsider intubation and ventilation if pH <7.26 and PaCO2 is rising \ndespite non-invasive ventilation only where appropriate (see \n\u2018Consider the ceiling of care\u2019 in text)\nFig 19.13 Management of acute COPD.\n*Load with 250mg over 20min, then infuse at a rate of ~500mcg/kg/h (300mcg/kg/h if elderly), where kg is \nideal body weight. Do not give a loading dose to patients on maintenance methylxanthines (theophyllines/\naminophylline; see p811). Check plasma levels if given for >24h. ECG monitoring is required.\n\u2020This may alone serve as a rescue therapy, be an intermittent step before ventilation, or be considered as a \n\u2018ceiling of therapy\u2019 for those deemed not suitable for mechanical ventilation.", "text_length": 1798, "metadata": {"source": "8205Oxford Handbook of Clinical Medicine 10th 2017 Edition_SamanSarKo - Copy.pdf (Part 821/905)", "type": "chunk", "chunk_index": 820, "total_chunks": 905, "uploaded_by": "admin@admin.com", "upload_date": "2025-12-11T17:59:53.605227", "document_uuid": "1c4b3c41-9a74-4d3d-ab11-d2a041c9641f", "filename": "8205Oxford Handbook of Clinical Medicine 10th 2017 Edition_SamanSarKo - Copy.pdf", "category": "medical_pdf", "section": "body", "year": 2017, "outdated": false, "document_id": "1c4b3c41-9a74-4d3d-ab11-d2a041c9641f"}, "created_at": "2025-12-11T17:59:53.605951", "status": "complete", "chunks_added": 1}