{"task_id": "acc5954b64c00b6d", "source": "8205Oxford Handbook of Clinical Medicine 10th 2017 Edition_SamanSarKo - Copy.pdf (Part 422/905)", "text": "egnant, antibiotic \ntherapy, DM, immunosuppressed.\n\n--- Page 428 ---\n414\nInfectious diseases\nFever in the returning traveller\n\ue007 Exclude malaria in all travellers from the tropics (p416\u20139).\n\ue007 Exclude HIV in all (p398).\n\ue007 Most travellers have self-limiting illnesses that could have been acquired in UK. \nLook for tropical infection9 but don\u2019t forget your usual diff erentials.\nHistory Detailed geography of travel (table 9.17)9 including setting (rural/urban), \ntime of onset of symptoms, duration of symptoms (table 9.18).9 Ask about activities \nand events: bites, diet, fresh-water exposure (schistosomiasis, leptospirosis), dust \nexposure, sexual activity, game parks (tick typhus, anthrax, trypanosomiasis), farms, \ncaves (histoplasmosis, rabies, Ebola), unwell contacts.\nAssociated symptoms:\n  \n\u2022 Respiratory: S. pneumoniae, H. in\ufb02 uenzae, legionella, in\ufb02 uenza, viral respiratory \ndisease (SARS, MERS), TB, HIV-associated disease, melioidosis.2\n  \n\u2022 Neurological: malaria, meningococcal meningitis, HIV, syphilis, Lyme disease, lep-\ntospirosis, brucellosis, tick-borne encephalitis, relapsing fever, trypanosomiasis.\nTable 9.17 Diff erential diagnosis by geography\nArea of travel\nCommon\nOccasional\nRare but do not miss \nSub-Saharan \nAfrica\nMalaria (pp416\u20139)\nHIV (pp398\u2013403)\nRickettsiae (p422)\nSchistosomiasis (p434)\nAmoebiasis (p432)\nBrucellosis (p424)\nDengue (p420)\nEnteric fever (p415)\nMeningococcus (p390)\nOther arbovirus (p420)\nTrypanosomiasis (p423)\nVHF (pp426\u20137)\nVisceral leishmaniasis \n(p423)\nSouth-East \nAsia\nMalaria (pp416\u20139)\nChikungunya (p420)\nDengue (p420)\nEnteric fever (p415)\nLeptospirosis (p425)\nMelioidosis2\nHanta virus (p426)\nJapanese encephalitis \n(p436)\nRickettsiae (p422)\nScrub typhus (p422)\nSouth and \nCentral Asia\nMalaria (pp416\u20139)\nDengue (p420)\nEnteric fever (p415)\nChikungunya (p420)\nVisceral leishmaniasis \n(p423)\nVHF (CCHF) (pp426\u20137)\nRickettsiae (p422)\nJapanese encephalitis \n(p436)\nMiddle East \nMediterranean \nNorth Africa\nBrucellosis (p424)\nQ-fever (p424)\nZika (p421)\nVisceral leishmaniasis \n(p423)\nSouth America\nCaribbean\nMalaria (pp416\u20139)\nDengue (p420)\nEnteric fever (p415)\nBrucellosis (p424)\nLeptospirosis (p425)\nZika (p421)\nTrypansomiasis (p423)\nHanta virus (p426)\nYellow fever (p420)\nEastern\nEurope\nScandinavia\nLyme disease (p422)\nHanta virus (p426)\nTick-borne encephalitis\nAustralia\nDengue (p420)\nQ fever (p424)\nRickettsiae (p422)\nMelioidosis2\nNorth America\nLyme disease (p422)\nRickettsiae (p422) \nMelioidosis2\nTable 9.18 Diff erential diagnosis according to incubation time\nIncubation period\nInfections\nShort <10d\nDengue, chikungunya, gastroenteritis, relapsing fever, rickettsiae\nMedium 10\u201321d\nMalaria, HIV, brucellosis, enteric fever, leptospirosis, melioidosis, \nQ-fever, coccidioidomycosis, VHF, Chagas\u2019 disease, trypanosomiasis\nLong >21d\nMalaria, HIV, TB, viral hepatitis, brucellosis, schistosomiasis, amoe-\nbic liver abscess, trypanosomiasis, visceral leishmaniasis\nChronic fever <14d\nTB, HIV plus opportunistic infection, pyogenic deep seated abscess, \ninfective endocarditis, brucellosis, enteric fever, fungal infection, \nschistosomiasis, visceral leishmaniasis, PE\n2 Burkholderia pseudomallei in tropical water/soil. Causes pneumonia, pleural eff usions, pulmonary \nabscess. Systemic abscess if haematogenous spread: liver, spleen, skin, muscle. Treat with co-amoxiclav, \ndoxycycline, co-trimoxazole. In severe disease: ceftazidime, meropenem.", "text_length": 3393, "metadata": {"source": "8205Oxford Handbook of Clinical Medicine 10th 2017 Edition_SamanSarKo - Copy.pdf (Part 422/905)", "type": "chunk", "chunk_index": 421, "total_chunks": 905, "uploaded_by": "admin@admin.com", "upload_date": "2025-12-11T17:59:52.899303", "document_uuid": "1c4b3c41-9a74-4d3d-ab11-d2a041c9641f", "filename": "8205Oxford Handbook of Clinical Medicine 10th 2017 Edition_SamanSarKo - Copy.pdf", "category": "medical_pdf", "section": "body", "year": 2017, "outdated": false, "document_id": "1c4b3c41-9a74-4d3d-ab11-d2a041c9641f"}, "created_at": "2025-12-11T17:59:52.900118", "status": "complete", "chunks_added": 2}